modpacker/__init__.py
modpacker/api.py
modpacker/cache.py
modpacker/commands/add.py
modpacker/commands/update.py
modpacker/compile.py
modpacker/config.py
modpacker/log/multi_formatter.py
modpacker/log/tqdm_wrapper.py
modpacker/migration.py
modpacker/modpacker.py
modpacker/packer_config.py
modpacker/server.py
modpacker/services/curseforge.py
modpacker/services/modrinth.py
modpacker/services/packwiz.py
modpacker/services/provider.py
modpacker-0.1.7.dist-info/WHEEL
modpacker-0.1.7.dist-info/entry_points.txt
modpacker-0.1.7.dist-info/METADATA
modpacker-0.1.7.dist-info/RECORD
