Metadata-Version: 2.3
Name: modpacker
Version: 0.1.7
Summary: The best Minecraft modpack creation tool you know
Classifier: Development Status :: 2 - Pre-Alpha
Classifier: Programming Language :: Python :: 3
Requires-Dist: click
Requires-Dist: requests
Requires-Dist: tqdm
Requires-Dist: tomli-w
Requires-Dist: questionary>=2.1.1
Requires-Dist: brotli>=1.2.0
Requires-Dist: jsonschema>=4.26.0
Requires-Python: >=3.11
Project-URL: source, https://github.com/Kinsteen/packer
